pingsss/__init__.py
pingsss/pingsss.py
pingsss-1.1.dist-info/METADATA
pingsss-1.1.dist-info/WHEEL
pingsss-1.1.dist-info/entry_points.txt
pingsss-1.1.dist-info/top_level.txt
pingsss-1.1.dist-info/RECORD
